darca_yaml/__init__.py
darca_yaml/__version__.py
darca_yaml/yaml_utils.py
darca_yaml-0.2.0.dist-info/LICENSE
darca_yaml-0.2.0.dist-info/METADATA
darca_yaml-0.2.0.dist-info/WHEEL
darca_yaml-0.2.0.dist-info/RECORD
