Metadata-Version: 2.3
Name: darca-yaml
Version: 0.2.0
Summary: YAML utilities for reuse along projects.
License: LICENSE
Author: Roel Kist
Author-email: roel.kist@gmail.com
Requires-Python: >=3.12,<4.0
Classifier: License :: Other/Proprietary License
Classifier: Programming Language :: Python :: 3
Classifier: Programming Language :: Python :: 3.12
Classifier: Programming Language :: Python :: 3.13
Requires-Dist: cerberus (>=1.3.7,<2.0.0)
Requires-Dist: darca-exception (>=0.1.0,<0.2.0)
Requires-Dist: darca-file-utils (>=0.1.0,<0.2.0)
Requires-Dist: darca-log-facility (>=0.1.0,<0.2.0)
Requires-Dist: pyyaml (>=6.0.2,<7.0.0)
